{
    "FSU-HYCOM":{
	"path":"../model/FSU-HYCOM/20190724",
	"fname":"surf_monthly_xyt_6thcycle_jra55_fsu.nc",
	"name":"zos",
        "undef":"1e30",
        "undefnan":"False",
	"gtorlt":"gt",
	"londim":"lon",
	"latdim":"lat",
	"lonname":"longitude",
	"latname":"latitude"
    },
    "CAS-LICOM3":{
	"path":"../model/CAS-LICOM3/20190731",
        "fname":"OMIP2_zos_306To366_monthly_remapycon.nc",
        "name":"zos",
        "undef":"9.9e34",
        "undefnan":"False",
	"gtorlt":"gt",
	"londim":"lon",
	"latdim":"lat",
	"lonname":"lon",
	"latname":"lat"
    },
    "AWI-FESOM":{
	"path":"../model/AWI-FESOM/20190731/OMIP2/loop6",
        "fname":"zos_Omon_FESOM1.4_historical_loop6_gr_195801-201812.nc",
        "name":"zos",
        "undef":"0.99e20",
        "undefnan":"False",
	"gtorlt":"gt",
	"londim":"lon",
	"latdim":"lat",
	"lonname":"lon",
	"latname":"lat"
    },
    "CESM-POP":{
	"path":"../model/CESM-POP/20190731/omip2",
        "fname":"zos_Omon_CESM2_omip2_r1i1p1f1_gr_030601-036612.nc",
        "name":"zos",
        "undef":"0.99e20",
        "undefnan":"False",
	"gtorlt":"gt",
	"londim":"lon",
	"latdim":"lat",
	"lonname":"lon",
	"latname":"lat"
    },
    "NorESM-BLOM":{
	"path":"../model/NorESM-BLOM/20190814",
        "fname":"zos_jra_20190804_WOA.nc",
        "name":"zos",
        "undef":"-1.0e34",
        "undefnan":"True",
	"gtorlt":"gt",
	"londim":"x",
	"latdim":"y",
	"lonname":"lon",
	"latname":"lat"
    },
    "MRI.COM":{
	"path":"../model/MRI.COM/20190809/omip2",
	"fname":"zos.nc",
	"name":"zos",
	"undef":"-9.00e33",
        "undefnan":"False",
	"gtorlt":"lt",
	"londim":"lon",
	"latdim":"lat",
	"lonname":"lon",
	"latname":"lat"
    },
    "EC-Earth3-NEMO":{
	"path":"../model/EC-Earth3-NEMO/20191128/OMIP2_new_realization/loop6",
        "fname":"zos_Omon_EC-Earth3_omip1_r1i1p1f1_gn_195801-201812_WOAgrid.nc",
        "name":"zos",
        "undef":"0.99e20",
        "undefnan":"False",
	"gtorlt":"gt",
	"londim":"lon",
	"latdim":"lat",
	"lonname":"lon",
	"latname":"lat"
    },
    "Kiel-NEMO":{
	"path":"../model/Kiel-NEMO/20190902",
        "fname":"GEOMAR05.JRAbgc-cycle6_1m_19580101_20181231_zos.nc",
        "name":"zos",
        "undef":"0.99e20",
        "undefnan":"True",
	"gtorlt":"gt",
	"londim":"lon",
	"latdim":"lat",
	"lonname":"lon",
	"latname":"lat"
    },
    "GFDL-MOM":{
	"path":"../model/GFDL-MOM/20191003/OMIP2",
        "fname":"monthly_tos_sos_zos_lastcycle_JRA.nc",
        "name":"zos",
        "undef":"0.99e20",
        "undefnan":"False",
	"gtorlt":"gt",
	"londim":"lon",
	"latdim":"lat",
	"lonname":"lon",
	"latname":"lat"
    },
    "CMCC-NEMO":{
	"path":"../model/CMCC-NEMO/20191109/OMIP2",
        "fname":"OMIP2.1d_CMCC_1m_zos_195801_201812.nc",
        "name":"zos",
        "undef":"0.99e20",
        "undefnan":"False",
	"gtorlt":"gt",
	"londim":"lon",
	"latdim":"lat",
	"lonname":"lon",
	"latname":"lat"
    }
}
